{
  "الكلمة اللبنانيّة (لهجة بيروت)": "معناها",
  "بشوف": "أرى أو أنا شايف.",
  "خزّق": "للدلالة على التمزّق (أي \"مزّق\").",
  "هلأ/ هلق": "الآن أو هذه الساعة.",
  "مخزن/ دكان صغير": "غرفة صغيرة أو مكان صغير لتخزين المؤونة والأشياء قليلة الاستعمال.",
  "منيح": "أي الشيء الجيد أو الحسن.",
  "اسكت": "أغلق فمك.",
  "اسکربینة": "تستخدم للدلالة على \"الحذاء النسائي\". في اللهجة الحديثة قد يُقال “شوزة” أو “جزمة نسائية” حسب السياق.",
  "اقصفتلي ركبي": "يعني فزعتني أو أخفتني وأرعبتني؛ أي جعلتني أفقد ثباتي من الدهشة أو الخوف.",
  "اِجِر/ رجول": "القدم/ الأرجل.",
  "الّ": "يُستعمل للدلالة على مسؤول حكومي أو ضابط رتبته عالية؛ وفي الحديث اليومي يقولون “ضابط”.",
  "اويها": "تُستخدم للدلالة على الفرح والبهجة؛ في بيروت ممكن أن يُقال مثلاً “مبسوط كتير” أو “فرحان” حسب السياق.",
  "بَلْكِي": "تعني يمكن أو ربما.",
  "بِس": "تُقصد بها \"قط\" أي القطة (مفرد).",
  "بسة": "قطة (المؤنث).",
  "بساس": "جمع \"بسة\"، أي \"قطط\".",
  "بلّش": "بدأ.",
  "تقبرني": "تعبير دعائي يعني \"الله يطول بعمرك\".",
  "شوية": "القليل من.",
  "حتن": "حتى.",
  "خِتْيَارْ": "تُقال للدلالة على الشخص الكبير أو المسن، أي \"شيخ\" (رجل كبير).",
  "خِتْيَارَة": "\"شيخة\" أي امرأة كبيرة في السن.",
  "دخيل": "تُقال للتعجب، ويمكن أن تُستعمل عبارة مثل “يا لطيف” للتعبير عن الدهشة.",
  "دخيلك": "تُقال بمعنى \"لو سمحت\" أي طلب مهذب.",
  "زغنون": "\"الصغير\"؛ تُستخدم للدلالة على الشخص الصغير بالعمر.",
  "زحطي": "تُقال “روحي” أي \"اذهبي\"، وهو أمر يُوجه للإناث.",
  "سيدا": "تعني مستقيم أو باتجاه مستقيم.",
  "شاضوم": "تعني \"فضولي\" أي الشخص الذي يتدخل فيما لا يعنيه.",
  "شو بدك؟": "ماذا تريد؟",
  "ضيعة": "قرية.",
  "طحبش": "كسّر؛ أي حطّم أو أضر.",
  "عيب الشوم": "تعبير يعني عيب أو غير مقبول؛ يُستخدم للدلالة على العيب.",
  "كزدرة": "تمشية أو نزهة للترفيه.",
  "كماتنا": "مثلنا أو كما نحن.",
  "كماتو": "كما هو؛ أي على هذا النحو.",
  "مأزإز": "تعني يتجمد من البرد؛ أي أن الشخص أو الشيء يجمد نتيجة البرد الشديد.",
  "مَرَاقْ": "تُستخدم للدلالة على المزاج أو الاهتمام؛ بحسب السياق.",
  "نئزني": "فاجأني.",
  "نئزتني": "فاجأتني.",
  "هون": "هنا.",
  "هيدا": "تعني هذا أو هذه؛ بحسب السياق.",
  "وظّي": "تُستخدم للدلالة على أن سلوك شخص أو كلامه مش محترم أو غير لائق.",
  "وينتا": "تعني إيمتى أي متى.",
  "يا زلمة": "تُستخدم كما هي بمعنى يا رجل.",
  "يمخمض": "تعني يتمضمض بصوت عالٍ بطريقة مزعجة.",
  "يستك": "تعني مخدة كبيرة؛ أي الوسادة الكبيرة.",
  "الفرندا": "تُستعمل للدلالة على \"بلكونة\" أو \"شرفة\"؛ أي المكان الخارجي للجلوس أمام البيت.",
  "بيت المونة": "يُقصد به \"مخزن الطعام\"؛ غرفة تُستخدم لتخزين المواد الغذائية.",
  "الشطيح": "هو جلد أو قطعة قماش توضع عليها العجين لكي يختمر؛ يُمكننا وصفه بـ \"غطاء العجين\" أو \"لوح العجين\" بحسب السياق.",
  "الوجاق": "يُقصد به موقد يعمل على الحطب للتدفئة.",
  "الطراحة": "تعني فراش صغير يُمد على الأرض للجلوس أو الاسترخاء.",
  "نملية": "تعني خزانة الطعام أو دولاب حفظ الطعام مصنوع من الخشب بواجهة معدنية.",
  "الصوبيا": "تعني مدفأة تعمل على المازوت؛ أي أداة للتدفئة.",
  "المصطبة": "تعني بلكونة أو مكان جلوس أمام البيت.",
  "المربع": "يُقصد به غرفة المعيشة أو الجزء الأساسي من المنزل.",
  "الليوان": "تعني صالون أو غرفة جلوس داخل البيت.",
  "المكاري": "يُقصد به البائع المتجول الذي يدور بين القرى ليبيع بضاعته.",
  "بتمون": "تُستخدم كطريقة للرد على طلب خدمة، بمعنى إن الطلب رح ينفذ بطريقة خاصة أو مع مونة (مؤونة) خاصة؛ وهو تعبير دارج قد لا يكون له بديل دقيق لكنه يفيد معنى التقدير والخصوصية.",
  "لعيونك": "تُقال للدلالة على المحبة والتقدير لشخص عزيز؛ تعني \"من أجلك\" أو \"لعيونك\".",
  "يسلموا دييتك": "تعبير شكر يستخدم بمعنى \"يسلموا إيديك\"، أي \"الله يحفظ إيديك\".",
  "بالإذن": "أستأذن بالانصراف.",
  "العِلّية": "غرفة علوية أو السندرة.",
  "البدروم": "القبو أو الطابق السفلي.",
  "البِساط": "سجادة.",
  "البرندا": "الشرفة.",
  "الحظيرة": "زريبة للماشية.",
  "كنباية": "أريكة.",
  "خزانة الحائط": "خزانة داخل جدران الغرفة بلا باب، تغطيها ستارة.",
  "سِدّة": "مكان مرتفع داخل البيت مشيد بالخشب ويستخدم لحفظ المؤن.",
  "عتبة": "الحاجب الحجري السفلي أو العلوي لمدخل البيت.",
  "دِكّة": "مقعد خشبي كبير يوضع في غرفة الضيوف.",
  "مِسند": "يشبه الوسادة ولكنه أكبر ومحشو بالقش.",
  "مخدة": "تكاية.",
  "طنجرة": "وعاء معدني كبير يستعمل للطبخ.",
  "معجَن": "وعاء كبير يستعمل لحفظ الخبز.",
  "تلج": "ثلج.",
  "تسلم لي": "دعاء إلى الله كي يحفظ الشخص.",
  "داية": "المرأة التي تساعد في الولادة.",
  "طريق مختصرة": "الطريق المختصر.",
  "فرشخ": "مد ساقيه بعيدًا عن بعضهما.",
  "وسواس": "حالة نفسية تجعل الشخص يرتاب في أي شيء، خاصة النظافة.",
  "ترويقة": "وجبة الإفطار.",
  "اطلع": "فل.",
  "سئيل": "غليظ ومزعج.",
  "كباية": "كأس.",
  "معتّر": "فقير أو مسكين.",
  "أوضة": "غرفة..",
  "إيه": "أجل/ نعم.",
  "تخت": "سرير.",
  "ليك": "انظر.",
  "دغري": "مباشرة.",
  "وقعت": "فَرْكَشْت.",
  "تزنطر": "يتدخّل في ما لا يعنيه.",
  "شو بتريدي؟": "ماذا تريدين؟",
  "حنية": "حنان.",
  "تعا": "تعال.",
  "سهراتنا": "حفلاتنا.",
  "عربيتي": "سيارتي.",
  "نيقة": "يهتم بالتفاصيل.",
  "خبّرني": "انقل لي الأخبار.",
  "حدّي": "جانبي أو جواري.",
  "الحديقة": "الجنينة.",
  "استحليت": "أعجبني.",
  "بيعئد": "رائع.",
  "حايص": "محتار قلقان.",
  "شرشح": "وبّخ.",
  "حلّ عني": "ابتعد عني.",
  "ما خصنا": "ما دخلنا.",
  "لفاية": "خادمة أو شغالة.",
  "منمنم": "صغير جدًا.",
  "شو بك؟": "مالك؟",
  "يادلي": "يا إلهي.",
  "نبرم": "نلف",
  "جرصتني": "جلبت لي الفضيحة.",
  "لتّات": "كثير الكلام.",
  "بقشعك": "أراك.",
  "تشارعوا": "تضاربوا.",
  "تتلأمن": "تصبح لئيم.",
  "دنّق": "شعر بالبرد.",
  "لزقة": "شخص موجود وغير مرغوب فيه.",
  "كعيت": "طاولة صغيرة.",
  "الشتي": "الشتاء.",
  "يعمّر": "يبني.",
  "برنية": "وعاء فخاري صغير لحفظ الطعام.",
  "بقجة": "قشة، وكانت تصنع من القش.",
  "زت/ كب": "رمى.",
  "تتخيتي": "عليها.",
  "بعجور": "شمّام.",
  "مبلى": "أيوه.",
  "لَيك": "شوف.",
  "بعتل همك": "بشيل همك.",
  "تِصْطِفِل": "على راحتك.",
  "جُوا": "في الداخل.",
  "اشَطِت": "طيحت.",
  "زَبَّط": "ظبط.",
  "مكَرْكَب": "مخربط.",
  "عَجْأَة سير": "زحمة.",
  "نَوَّس": "خفف.",
  "فل": "هرب/ ذهب أو خرج.",
  "بكي شي": "فيكي شي.",
  "عيطيلها": "بنادي عليها.",
  "بعد": "كمان.",
  "بهداوة": "بهدوء.",
  "ولدنة": "حركات الأولاد.",
  "ما حدا لحدا": "كل واحد لحاله.",
  "ببقى": "بضل.",
  "قلبي انكوى": "قلبي احترق.",
  "يعبي": "يملأ.",
  "جايي": "قادم.",
  "طلع": "انظر.",
  "الحكاية": "القصة.",
  "بعلمي": "أنا بظن.",
  "يفضى": "يصبح فارغ.",
  "نطرني": "انتظرني.",
  "صبية": "فتاة.",
  "أزاز": "زجاج.",
  "صغيورة": "صغيرة.",
  "حاكينا": "احكي معنا.",
  "رفيق": "صديق.",
  "صوب": "باتجاه.",
  "فايق": "متذكر.",
  "ستي": "جدتي.",
  "ميكانسيان": "ميكانيكي سيارات.",
  "دلوني": "أرشدوني.",
  "مرسال": "رسالة.",
  "العربيي": "السيارة.",
  "افادة": "معلومة.",
  "بيي": "أبي.",
  "إمي": "أمي.",
  "حشورة": "متدخلة.",
  "هادا": "هذا.",
  "ماشي خلفاني": "تعبير يعني \"على خلاف المتبع\".",
  "بدّي": "أريد.",
  "هالزلمة": "هذا الرجل أو الشاب.",
  "شلونك": "كيف حالك.",
  "بريّ عليك": "أحسنت.",
  "شِنّوو": "لأنه.",
  "شغلة": "أمر أو حاجة.",
  "شغلات": "أمور أو حاجات.",
  "شو عليه": "لا بأس.",
  "يامو": "يا أمي.",
  "يابي": "يا أبي.",
  "أنو": "أنه.",
  "يعطيك العافية": "تعبير شكر يتضمن دعاء بالصحة والعافية.",
  "براغي": "المسامير.",
  "جوارير": "الأدراج.",
  "ضَهَر": "خرج أو راح.",
  "كفّي": "واصل أو كمّل.",
  "وجّ": "وجه.",
  "إجرك": "رجلك.",
  "إجرينه": "رجليه.",
  "مصاري": "فلوس.",
  "مصريات": "فلوس.",
  "عنّا": "عندنا.",
  "سمعان فيه": "سمعت عنه.",
  "هونيك": "هناك.",
  "سباط": "حذاء.",
  "إسبادريّ/ إسبادغي/ إسبادرين": "حذاء الرياضة.",
  "مشاية/ شحّاطة": "حذاء البيت.",
  "ما إله طعمي": "ما لها فائدة أو مالها معنى.",
  "عابكره": "في الصباح الباكر.",
  "ناصح": "سمين.",
  "كرمالك": "من أجلك أو كرامة لك.",
  "تلفن له/ عيط له": "اتصل به أو نادِ عليه.",
  "في إشي": "هل حدث شيء؟.",
  "أباضاي": "الرجل ذو القبضة القوية.",
  "ماني غضران": "لست قادرًا.",
  "مرئ هون": "مرّ من هنا.",
  "دخيل الله": "تعبير يُستخدم للاستغاثة بالله.",
  "شاطط وماطط": "تُستخدم للدلالة على التدليل المفرط.",
  "عقلو جوزتين بخرج": "تعبير يُشير إلى قلة الفهم.",
  "عجئة": "زحمة.",
  "مهضوم": "مرح أو خفيف الدم.",
  "جرصتنا": "فضحتنا.",
  "سخسخ": "ارتخى.",
  "طبطب": "ربت على كتفه.",
  "فتفت": "كسّر الشيء إلى قطع صغيرة.",
  "ربرب": "زاد وزنه.",
  "بربر": "تُستخدم بمعنى أكثر من الكلام.",
  "بحبح": "سخى وأكثر في الكمية.",
  "لحلح": "تحرك.",
  "حلحل": "فك العقدة أو لان في الرأي.",
  "طقطق": "تشقّق.",
  "فصفص": "أكل البزر أو أزال قشرة حص الثوم.",
  "دبدب": "سمن وزاد وزنه.",
  "بُعبُع": "وحش.",
  "بَعبَع": "تكلم بصوت عالٍ.",
  "تكتك": "عمل بدقّة وتمهّل.",
  "وشوش": "همس.",
  "سبسب": "شتم.",
  "جأجأ": "اتسخ.",
  "جهجه": "طلع الصباح.",
  "شدشد": "شدّ جيّداً.",
  "ضبضب": "رتّب.",
  "نهنه": "نضج أكثر من اللازم.",
  "هفهف": "نظيف ومتألّق.",
  "بظبظ": "أسرف.",
  "قبقب": "فك الإلتصاق عنه.",
  "بجبج": "تورّم الوجه عند الاستيقاظ أو المرض.",
  "بسبس": "نادى بصوت منخفض.",
  "بصبص": "تلصّص.",
  "بكبك": "تظاهر بالبكاء.",
  "خشخش": "استهبل أو أصابه الجنون.",
  "خضخض": "رجّ كثيراً.",
  "دسدس": "تحسس بيده.",
  "دقدق": "دق أكثر من مرة.",
  "رحرح": "أكثر وزاد الكمية.",
  "فكفك": "فك جميع أجزاء الجهاز.",
  "كشكش": "نهاية الثوب المزركشة.",
  "مدمد": "مد رجليه.",
  "نطنط": "أكثر من القفز.",
  "ولول": "علا صوته نحيباً.",
  "لزلز": "تلذّذ.",
  "جعجع": "أكثر من الأصوات العالية.",
  "جقجق": "استغاب وأكثر من الكلام الذي ليس له لزوم.",
  "غبغب": "شرب الماء.",
  "قصقص": "قص الشيء إلى أجزاء صغيرة.",
  "فضفض": "خفف ما في نفسه من ضغط.",
  "شرشر": "انسكب منه السائل.",
  "طشطش": "مسطول أو كسول.",
  "تشتش": "تبلّل وفقد قوامه.",
  "لعلع": "تكلم بصوت عالٍ.",
  "مخمخ": "فكّر بعمق.",
  "زهزه": "انتشى من المخدرات أو الكحول.",
  "كبكب": "تناثرت منه الأشياء.",
  "دغدغ": "لامس المشاعر.",
  "مزمز": "تناول الشراب على مهل.",
  "خمخم": "تعفّن.",
  "دندن": "غنّى.",
  "عجعج": "سمِنَ.",
  "عشعش": "سكن في المكان وتكاثر.",
  "عضعض": "عض أكثر من مرة.",
  "عنعن": "تذمّر.",
  "فسفس": "أقرّ عليه.",
  "فَلفَل": "طبخ الأرز.",
  "أزأز": "ارتجف من البرد.",
  "لتلت": "استغاب في الكلام.",
  "لفل": "احتال على القضية لينساها الناس.",
  "مجمج": "قبّل.",
  "نصنص": "وضعه في المنتصف تماماً.",
  "هزهز": "تأرجح.",
  "رشرش": "رش الماء أكثر من مرة.",
  "مرمر": "طعمه مر.",
  "شمشم": "شم.",
  "نقنق": "تذمّر.",
  "نفنف": "أخرج المخاط من أنفه.",
  "زكزك": "استفزّ.",
  "زرزر": "استفزّ.",
  "تأتأ": "تلعثم في الكلام.",
  "تختخ": "طال مكوثه في السجن أو اهترأ.",
  "سحسح": "ضَرَبَ على الرقبة.",
  "شطشط": "واسع.",
  "صحصح": "استفاق.",
  "جخيخ": "شيك.",
  "بأوسي": "بيفاجأك من الخلف.",
  "زَبَّط": "صلّح.",
  "بُكرا": "غداً.",
  "ترويئة": "فطور أو طعام بشكل عام.",
  "اضهر": "أخرج من البيت.",
  "مجوي": "وسخ.",
  "مألعط": "وسخ.",
  "سلم": "درج.",
  "مزنطر": "لباس ملفت للنظر.",
  "كبجاية": "معلقة السكب.",
  "حمة اللي بتنئرك نئر": "للذم.",
  "توئبورني": "للمدح.",
  "صباحو": "صباح الخير.",
  "يلّا نتروّق": "هيا نفطر.",
  "صبحية": "جلسة صباحية مع الأصدقاء والأهل.",
  "بدّي فل": "أريد الذهاب.",
  "روق ما بدّا هالقد": "اهدأ لا داعي لهذا القدر.",
  "اسطفل": "افعل ما شئت.",
  "فايت اتسطّح": "داخل للاستلقاء.",
  "مُطفي عالآخر": "نفدت طاقتي.",
  "يقبرني جمالك": "يعجبني جمالك.",
  "ما أطيبك": "ما أطيب قلبك.",
  "شو مهضوم": "روح طيبة.",
  "بتعقّد": "رائعة.",
  "بتجنّن": "مذهلة.",
  "لوين": "إلى أين.",
  "ما بيعرف الخمسة من الطمسة": "لا يعرف شيئاً.",
  "ياعيب الشوم": "عيب عليك.",
  "فضحتنا": "كشفت عيوبنا.",
  "جرّصتنا": "فضحتنا.",
  "قصفتلّي عمري": "أخفتني أو أرعبتني.",
  "بيلبقلي": "يناسبني.",
  "الحكي": "الكلام.",
  "جينا": "أتينا.",
  "سكربية": "حذاء نسائي.",
  "إنتَ/ إنتِ": "أنتَ/ أنتِ",
  "إنتو": "أنتم",
  "كيفَك/ كيفِك؟": "كيف حالك؟",
  "شو؟": "ماذا؟",
  "شو عم تعمل؟": "ماذا تفعل؟",
  "هيدا/ هيدي/ هيداك": "هذا/ هذه/ ذلك.",
  "هيك": "هكذا.",
  "بَس": "لكن/ فقط.",
  "لأ": "لا",
  "ماشي الحال": "الأمور بخير.",
  "يلا": "هيا.",
  "بعدني": "ما زلت.",
  "ليش؟": "لماذا؟",
  "ما بعرف": "لا أعرف.",
  "زلمي": "رجل.",
  "شبّ": "شاب.",
  "عالبكلة": "تمامًا/ بالضبط.",
  "عنجد؟": "حقًا؟",
  "مظبوط": "صحيح.",
  "إمزح": "أمزح.",
  "فلّ/ فلّي": "غادر/ غادري.",
  "مش معقول!": "غير معقول!",
  "هيدا الشي بيجنّن": "هذا الشيء رائع جدًا.",
  "ناطر/ ناطرتك": "أنتظرك.",
  "شو القصة؟": "ما الأمر؟",
  "ما خصّك": "لا علاقة لك.",
  "تعا/ تعَي": "تعالَ/ تعالي.",
  "روق/ روقي": "اهدأ/ اهدئي.",
  "إنتَ أشطر واحد!": "أنتَ الأفضل!",
  "حاجِك بقا": "يكفي/ توقف.",
  "كتير": "كثير.",
  "اشتقلتَك/ اشتقلتِك": "اشتقت لك.",
  "شو رأيَك؟": "ما رأيك؟",
  "ولا يهِمَّك": "لا تقلق.",
  "ما إلي خِلق": "لا أشعر بالرغبة/ القدرة.",
  "النطق": "ينطق كما هو في اللغة الفصحى.",
  "بئر": "بير",
  "ذئب": "ديب",
  "رأس": "راس",
  "دواء": "دوا",
  "بريء": "بري",
  "ملأ": "ملا",
  "تفاح": "تِفاح",
  "ثورة": "سَورة",
  "ثواني": "سَواني",
  "ثانية": "تانية",
  "كثير": "كتير",
  "كذاب": "كزاب.",
  "ذهب": "دهب.",
  "ظريف": "زريف",
  "ظلام": "ضلام",
  "لذيذ": "لزيز.",
  "نحن": "نحنا.",
  "يد": "إيد.",
  "صحيح": "\"بعد ما خلّصت الشغل.\" (لم أنتهِ من العمل بعد.)",
  "خطأ": "\"بَعَد ما خلّصت الشغل.\"",
  "الأخطاء المتكررة (الخطأ": "الصح)",
  "إيش": "شو.",
  "إذن": "إزن.",
  "كل": "كول.",
  "ألبس": "لبوس.",
  "جاء": "إجا.",
  "أحكي": "حكي.",
  "أعمل": "عمول.",
  "كيف حالك": "كِيفك cava.",
  "هسا": "هلأ.",
  "لا أريد": "ما بدي.",
  "لا يوجد": "ما في.",
  "لماذا": "ليه.",
  "مش قادر": "مَنّي قادر.",
  "خبر": "خبريه.",
  "قاعدة أعيشها": "عم عيشا.",
  "اختار": "نئي.",
  "ثقيل دم": "سئيل.",
  "أناديك": "اعيطلك.",
  "حبيتها": "حبيتا.",
  "شايفيتيني": "ئاشعيتني.",
  "قطرميز": "مرتبان.",
  "دولة": "ركوة.",
  "مجرود": "لقاطة.",
  "ليمون": "حاموض.",
  "بابوج": "شحاطة.",
  "جنينة": "حديئة.",
  "على بلاطة": "من الاّخر.",
  "كاسة": "كباية.",
  "حِدة": "حَارّه.",
  "فاصوليا": "لوبيا.",
  "شاكريه": "لبن إمه.",
  "زبدية": "كاسة.",
  "برتقال": "ليمون.",
  "داسوس": "جاسوس.",
  "دايق خلقي": "ضايج.",
  "طوشة": "خنائة.",
  "إيمتى": "إيمتين.",
  "زحط": "أشط.",
  "تأشر": "تشوبر.",
  "طاولة": "سكملة.",
  "صوبة": "صوبية.",
  "جربات": "كلسات.",
  "سنسال": "عقد.",
  "نضارات": "عوينات.",
  "بندورة": "بَنَدُورة.",
  "كندرة": "سباط.",
  "طالعين": "ضاهرين.",
  "بلوزة": "كنزة.",
  "سفرطاس": "ترمس أكل.",
  "بكلة": "دبوس.",
  "شنتة": "بقجة.",
  "أنف": "منخار.",
  "حياة": "حييت.",
  "ثلاجة": "برّاد.",
  "فريزر": "تلاجة.",
  "عجلة": "دولاب.",
  "زبادي": "لبن.",
  "بوت": "سبترين.",
  "جزمة": "بوت.",
  "مئشة": "مكنسة.",
  "جزدان": "بورتمونيه.",
  "حزام": "أشاط.",
  "ما إلي علاقة": "ما خصني.",
  "شيخ المحشي": "كوسا بلبن.",
  "زهرة": "إرنبيط.",
  "كلمتني": "تلفنتلي.",
  "أجاص": "إنجاص.",
  "لفة": "كزدورة.",
  "اهدا": "طَوَّل بَالَك.",
  "ظل": "فيّ.",
  "طنشه": "طربشله.",
  "رجال": "زلمة.",
  "حر": "شوب.",
  "انتقائي": "نيئة.",
  "مدرّسة": "معلّمة.",
  "بشكير": "منشفة.",
  "مضحك": "مهضوم.",
  "شو مالك": "شوبيك.",
  "زجاجة": "ئنينة.",
  "يخنة": "ملفوف.",
  "حزام الأمان": "سنتور.",
  "بربيش": "نبريش.",
  "مميزة": "سبيسيال.",
  "درج": "جارور.",
  "تكلمت عنها": "حكيتا.",
  "اقعد": "اتفتل.",
  "ادخل": "اتفضل.",
  "حادث": "حادس.",
  "سندويشة": "صندويشة.",
  "تصرف مصاري": "تشئف مصاري.",
  "راحة": "فشّة خلق.",
  "لسة ما فهمت": "بعدك ما فهمت.",
  "سترى": "راح تِشوف.",
  "بيستحق": "بيِسْتَاهِل.",
  "من هنا إلى هنا": "مِن هون لهون.",
  "انطلق": "قَلِّع.",
  "مميز": "مِشْ عَادِي.",
  "موافق": "أوكيه.",
  "مش مظبوط": "مُو زَابِط.",
  "نجحت": "ضَرَبْتْ مَعَك.",
  "الحال جيد": "ماشي الحال.",
  "غير قادر": "مَشْ قَادِر.",
  "تشعر بالألم": "مِتْوَجِّع.",
  "ليس لهذه الدرجة": "مُو لِهَالْدَرَجَة.",
  "سعيد": "مْبَسْوط.",
  "يا رجل": "يَا زَلَمِ.",
  "إلى أين ستذهب؟": "وِينْ رَحْ تِروح؟.",
  "عملته": "سَوَّيْتِه.",
  "يا أخي": "يَا خَييّ.",
  "لم أتكلم": "مَا حِكِيت.",
  "خيبت أملي": "خَيْبَتْنِي.",
  "لا عليك": "مَا عَلَيْك.",
  "ليس": "مِش.",
  "عملي": "شُغْلَتِي.",
  "من هذه اللحظة": "مِنْ هِيّك.",
  "تجعل الأمور أفضل": "تِجْبَرْ.",
  "أعرف": "عارِفْ.",
  "تأتي": "تِجِي.",
  "انتهينا": "خَلِّصْنَا.",
  "اتذوق": "دوء.",
  "ما بقدر": "ما فيي.",
  "بقدونس": "بئدونس.",
  "هذه": "هيدي/ هي.",
  "تلك": "هيدي.",
  "ذلك (للجمع)": "هيدول.",
  "الذي، التي، اللذين، اللواتي": "اللي.",
  "وضعت": "حطيت.",
  "الباذنجان": "البيتنجين.",
  "نطبق": "نرص.",
  "فيكم": "فيكون.",
  "بهذه الاثناء": "بهي الاسناء.",
  "افوكادو": "افوكا.",
  "مخلل": "كبيس.",
  "ما يغطى به النافذة": "برداية.",
  "زعل": "برطم.",
  "غول": "بُعبع.",
  "مشكلة": "ورطة، بَلشِة.",
  "مزاج": "نَفْسِيَّة.",
  "بدي": "حَابْب.",
  "زهقان": "مَلَان.",
  "تفضل": "خِد لَك.",
  "تضيع منه": "بَتْرُوح عَليْه.",
  "دمَّرته": "خَرَّبَتْه.",
  "منزعج": "متدايق.",
  "يشعر بالحر": "شَوْبَان.",
  "يشعر بالبرد": "بَرْدَان.",
  "مفلس": "مِنْتُوف.",
  "أب": "بْيِه.",
  "زعلان": "حَرْدَان.",
  "موضوع طويل": "قِصَّة.",
  "يغش": "عَمْ يِزْرُف.",
  "بدون فايدة": "بَلا طَعْمِة.",
  "فوضوي": "مْبَهْبَط.",
  "سعيد جداً": "مْكَيَّف.",
  "يتحدّث كثيراً بدون معرفة حقيقية": "عَمْ يِتْفَلْسَف.",
  "بقول كلام بدون معرفة": "خَبَّص.",
  "لا تضخّم الأمور": "ما تْكَبِّر القَصَّة.",
  "يتذاكى": "عَمْ يِتْشَاطَر.",
  "كلام بلا معنى": "حَكِي فَاضِي.",
  "ما في داعي لهاد الكلام": "بْلا هَالحَكي.",
  "غيّر الأمور": "شَقْلَب.",
  "هرَب": "شَحْوَط.",
  "ضحك كثير": "فَطَّس من الضَحِك.",
  "أزعجني": "حَرقصني.",
  "اضغط": "كَبِّس.",
  "بحالة فوضى": "مْعَجَّأ.",
  "طالع": "مْعَرْبَش.",
  "بيشتكي": "بينَقّ.",
  "طبعاً": "لَكَان.",
  "ضبط الأمور": "دَوزِن.",
  "فاجأه": "نَقْزَة.",
  "رَشْفَة": "شَفْطَة.",
  "قبل الوقت": "بَكِّير.",
  "مجاناً": "بِبَلاش.",
  "مسترخي": "مْسَطِّح.",
  "اهتزّ": "رَجْرَج.",
  "تناثر": "طَرْطَش.",
  "انبسط": "فَرفَح.",
  "لا تشغل بالك": "ما تْهَكِّل هَمّ.",
  "بدون وجع رأس": "بْلا صَرْعَة.",
  "سهلة": "هَيْنِة.",
  "شكراً لك": "كِلِّك زُوء.",
  "باختصار": "بَلا طول سيرة.",
  "دَوَّر": "فَتَّش.",
  "مُرتَبِك": "مْتَلبِّك.",
  "زلق": "زَحَطْ.",
  "مغرور": "مْعَنطَز.",
  "راح بسرعة": "شَلَف.",
  "مش مرتب": "مْبَهْدَل.",
  "قطعة صغيرة": "فَتْفُوتِة.",
  "محترم": "مِهَزِّب.",
  "نبش": "نَكِش.",
  "ضحكت فجأة": "فَقَعِت ضَحْكِة.",
  "جوعان كتير": "مْصَوِّص.",
  "مش مهتم": "مْطَنِّش.",
  "انتقاد سلبي": "قَضَف.",
  "تعبان كتير": "مْكَسَّر.",
  "خايف": "مْنَقِّز.",
  "متمدد": "مْسَطِّح.",
  "متكبر": "مْفَرْعِن.",
  "صوّب": "نَشَّن.",
  "خفف ضغط": "نَزِّل حِمِل.",
  "بتفلسف كتير": "مْفَزْلَك.",
  "مرتب": "مزنكر.",
  "مُدلّى": "مْدَنْدِل.",
  "صحّا من النوم": "فَيِّق.",
  "مضاعف": "مْدَوْبَل.",
  "مشان": "كَرْمَال.",
  "يا دَلّي": "يا غالي.",
  "قديم": "مْكَرْكَع.",
  "مربوط بقوة": "مْزَنْزَر.",
  "قطعة": "شَقْفِة.",
  "مجعد": "مْكَرْمِش.",
  "مشمئز": "مْقَزْزَ.",
  "دايخ": "مْدَرْوَخ.",
  "مقرمش": "مْقَرْقَش.",
  "كتير أكل": "مْبَلْبَع.",
  "كتير حلو": "مْسَوْكَر.",
  "كتير شارب مي": "مْفَشْفَش.",
  "اتحمم": "روّش.",
  "احفظ": "سيِّف.",
  "شارك": "شيّر.",
  "اعمل لايك": "ليّك.",
  "ابحث": "غوغّل.",
  "طرق حكي": "فيّل.",
  "صاحب مشاكل": "أزعر.",
  "ما إله قيمة": "ما بيسوى.",
  "جمعة صباحية": "صبحية.",
  "مزاجه مش رايق": "معوكر.",
  "لا تضغط/ لا تزيد بردة الفعل": "ما بدا هالئد.",
  "حكي كتير": "لتّ حكي.",
  "سيارة مرسيدس": "شبح/ أم عيون.",
  "سيارة بي ام": "الوطواط.",
  "سيارة هوندا": "المكواية.",
  "منفضة سجاير": "تبسة.",
  "عصبي": "نرفوز.",
  "شحاطة": "سرموجة.",
  "بعدي عنه": "احلقيله/ زحطيله.",
  "أخذنا كل مصاريه": "مشّطنا/ نشرنا.",
  "عفوا": "تكرم.",
  "رد للتحدي بالكلام": "فشرت.",
  "روح من هون": "زحّط.",
  "اتفضل": "شرّف.",
  "بداية كل جملة": "دَخلْلَك.",
  "وسع لنقعد": "لز.",
  "ينط من مكان لمكان": "فز.",
  "مكان": "مطرح.",
  "يتلذذ": "مز.",
  "للجرح بنزل دم": "نز.",
  "قطع طولية": "حِزّ.",
  "حرك الشي": "دِزّ.",
  "قص": "جزّ.",
  "شك الشي": "غِزّ.",
  "عز الشي": "عِزّ.",
  "شدّ ع اسنانه": "كزّ.",
  "الشارع الضيق": "زقاق.",
  "ملعقة اللبن": "كفكير.",
  "ندهن": "نطرش.",
  "ابعد عني": "حلّ عني.",
  "مايل": "لاوي.",
  "لايق": "لابع.",
  "ارمي": "زتّ.",
  "استنى/ انتظر": "انطر.",
  "ردح": "شرشح.",
  "مالك": "شبك.",
  "متذايق": "حايص.",
  "اعمل اللي بدك ياه": "اصطفل.",
  "ما بيتعوض": "لقطة.",
  "تسوق": "شوبنغ.",
  "السواقة": "السويئة.",
  "مش جاي عبالي": "مش طايق.",
  "تحتاج": "تعوز.",
  "فليفلة حارة": "حرّ.",
  "يومك": "نهارك.",
  "اثبت ع رأي": "ارسك عبر.",
  "يروح او ينقطع": "يقطش.",
  "قوي": "قبضاي.",
  "يا دوب": "انجئ.",
  "كركبة": "حراديء.",
  "موسخ": "مشرشح.",
  "يحرك ايديه للشرح": "يشوبر.",
  "يا ريت": "علواه.",
  "عايف حاله": "مشحر.",
  "مربط": "مكبرج.",
  "زاكي": "طيبة.",
  "سدة": "تتخيتة.",
  "لبن": "حليب.",
  "جرابين": "كلسات.",
  "ما بدي اشي": "بديش شي.",
  "مكتة": "منفضة.",
  "صراخ": "عياط.",
  "بدي اطلع/ اطش": "بدي اضهر.",
  "لف": "ابرم.",
  "تيتا": "ستي.",
  "هؤلاء": "هيدول/ هول.",
  "دمه ثقيل": "شو سميك.",
  "اكتب": "كتوب.",
  "انتظر": "نطور.",
  "بحبكم": "بحبكن.",
  "لباس": "تياب.",
  "مؤلم": "بوجع.",
  "ممكن": "فيكم.",
  "غير جميلة": "منا حلوة.",
  "غير نظيفة": "وخمة.",
  "شخص قوي": "أبضاي.",
  "بسرعة": "قوام.",
  "يوسف أفندي": "كلمنتين.",
  "رنيت": "تلفنت.",
  "تمشاية": "كزدورة.",
  "يختصر طريق": "يزورب.",
  "شبشب": "شحاطة.",
  "بوط": "سبدرين.",
  "أشاطة": "أحاطة.",
  "لاصق": "لزيق.",
  "بركة": "بيسين.",
  "هيو هنا": "ليكا هون.",
  "أخي": "خيي.",
  "صعب الإرضاء": "نيئة.",
  "بردت": "دنقت.",
  "علق": "تلتت.",
  "وسخ": "مألعط.",
  "بحمل همك": "بعتل همك.",
  "الدنيا": "الدني.",
  "فيكي شي": "بيكي شي.",
  "كلمه على التلفون": "تلفن له.",
  "فضحتني": "جرصتني.",
  "تشير": "تشوبر.",
  "فاجئني": "نأزني.",
  "جميل": "امور.",
  "تهتم": "تعتل.",
  "أحمق": "أجدب.",
  "تاكل كتير": "فجعانة.",
  "قبعة": "برنيطة.",
  "مشاني": "كرمالي.",
  "نصاب": "بلطجي.",
  "نافذة صغيرة": "طاقة.",
  "فم": "نيع.",
  "اقفز": "نط.",
  "طلبها للزواج": "طلب ايدا.",
  "شايف حاله": "معنطز.",
  "شفاه": "شفاتير.",
  "بائع قهوة": "قهوجي.",
  "صاحب دكانة": "دكنجي.",
  "بائع حلويات": "حلونجي.",
  "بتستاهل": "خرجك.",
  "بترول/ بنزين": "مازوت.",
  "صيدلية": "اكزخانة.",
  "نام على بطنك": "انبطح.",
  "شاب شجاع": "ابضاي.",
  "جميل جدا": "بتعقد.",
  "يصرخ بصوت عالي": "يجعر.",
  "أجنحة": "جوانح.",
  "على راحتك": "تصِطِفل.",
  "بدي روح": "بدي فل."
}